warning_ff_impl/rtl/cells.v
//============================================================
// cells.v -- flip-flop variants under comparison
//   1. dff_cell     : plain D flip-flop  (baseline)
//   2. razor_cell   : Razor FF, error-free-operation model
//   3. warning_cell : reference Warning FF  (REPLACE with yours
//                     if your module/port names differ)
//============================================================

// ---------- 1. Plain D flip-flop (baseline) ----------
module dff_cell #(parameter W = 8) (
  input              clk,
  input              rst_n,
  input  [W-1:0]     d,
  output reg [W-1:0] q
);
  always @(posedge clk or negedge rst_n)
    if (!rst_n) q <= {W{1'b0}};
    else        q <= d;
endmodule

// ---------- 2. Razor flip-flop (baseline #2) ----------
// Error-free-operation model: main DFF + shadow latch on a
// delayed clock + XOR comparator. This is the configuration
// Ernst et al. measured for the ~3% error-free overhead.
// The restore mux is omitted (it does not switch when there
// are no errors); add it if you want to model recovery power.
module razor_cell #(parameter W = 8) (
  input              clk,
  input              clk_del,   // delayed clock (half period)
  input              rst_n,
  input  [W-1:0]     d,
  output reg [W-1:0] q,
  output             error
);
  reg [W-1:0] shadow;
  always @(posedge clk or negedge rst_n)
    if (!rst_n) q <= {W{1'b0}};
    else        q <= d;

  // transparent-high shadow latch on the delayed clock
  always @(*)
    if (clk_del) shadow = d;

  assign error = |(q ^ shadow);
endmodule

// ---------- 3a. dont_touch delay element ----------
// LEN buffers in series. Preserved at synthesis with
// set_dont_touch (see dc/synth.tcl). NOTE: a short chain will
// NOT realize a true Delta in silicon -- the length must be
// characterized/sized to hit your target delay. This models
// the AREA and POWER of the delay element honestly; it does
// not by itself prove the warning TIMING (do that with a
// gate-level SDF timing sim).
module delay_line #(parameter LEN = 4) (
  input  in,
  output out
);
  wire [LEN:0] n;
  assign n[0] = in;
  genvar i;
  generate
    for (i = 0; i < LEN; i = i + 1) begin : dl
      buf u_b (n[i+1], n[i]);
    end
  endgenerate
  assign out = n[LEN];
endmodule

// ---------- 3b. cross-coupled NOR SR latch ----------
module sr_latch (
  input  s,        // set   = (T_p AND WD)
  input  r,        // reset = per-cycle clear
  output q
);
  wire qb;
  nor u_n0 (q,  r,  qb);
  nor u_n1 (qb, s,  q);
endmodule

// ---------- 3c. Warning flip-flop (reference) ----------
// Monitors the most timing-critical bit (MSB of the adder).
// Replace this whole module with your finalized warning_ff if
// your internals differ -- the pipeline top only needs the
// ports (clk, rst_n, d, q, warning).
module warning_cell #(parameter W = 8) (
  input              clk,
  input              rst_n,
  input  [W-1:0]     d,
  output reg [W-1:0] q,
  output             warning
);
  // main capture (a plain DFF -- data path is untouched)
  always @(posedge clk or negedge rst_n)
    if (!rst_n) q <= {W{1'b0}};
    else        q <= d;

  wire mon = d[W-1];                 // critical bit

  // transition detector: D xor delayed-D -> T_p pulse (width ~Delta)
  wire d_del;
  delay_line #(.LEN(4)) u_dl (.in(mon), .out(d_del));
  wire t_p = mon ^ d_del;

  // guard-window generator: CLK and NOT(delayed CLK) -> WD = [0, t_d]
  wire clk_del;
  delay_line #(.LEN(3)) u_wd (.in(clk), .out(clk_del));
  wire wd = clk & ~clk_del;

  // window sampler: SR latch set when T_p overlaps WD, cleared each cycle
  wire set_pulse = t_p & wd;
  wire clr       = ~clk;
  sr_latch u_sr (.s(set_pulse), .r(clr), .q(warning));
endmodule

warning_ff_impl/rtl/pipeline.v
//============================================================
// pipeline.v -- identical small pipeline, three FF variants.
//
//   input regs (plain DFF) -> 8-bit adder (logic under test)
//                          -> monitored register
//                          -> output reg -> q_out
//
// Only the monitored register changes between the three tops,
// so every PPA difference isolates the flip-flop overhead.
// The adder is the critical path; sweep CLK_PERIOD to push it
// toward (and past) its timing limit.
//============================================================

// ---- Baseline: plain DFF on the monitored register ----
module pipe_dff (
  input        clk,
  input        rst_n,
  input  [7:0] a,
  input  [7:0] b,
  output [7:0] q_out
);
  reg  [7:0] ra, rb, rc;
  wire [7:0] sum, mon_q;

  always @(posedge clk or negedge rst_n)
    if (!rst_n) {ra, rb} <= 16'b0; else {ra, rb} <= {a, b};

  assign sum = ra + rb;              // logic under test

  dff_cell #(.W(8)) u_mon (.clk(clk), .rst_n(rst_n), .d(sum), .q(mon_q));

  always @(posedge clk or negedge rst_n)
    if (!rst_n) rc <= 8'b0; else rc <= mon_q;
  assign q_out = rc;
endmodule

// ---- Razor on the monitored register ----
module pipe_razor (
  input        clk,
  input        clk_del,
  input        rst_n,
  input  [7:0] a,
  input  [7:0] b,
  output [7:0] q_out,
  output       error
);
  reg  [7:0] ra, rb, rc;
  wire [7:0] sum, mon_q;

  always @(posedge clk or negedge rst_n)
    if (!rst_n) {ra, rb} <= 16'b0; else {ra, rb} <= {a, b};

  assign sum = ra + rb;

  razor_cell #(.W(8)) u_mon (.clk(clk), .clk_del(clk_del), .rst_n(rst_n),
                             .d(sum), .q(mon_q), .error(error));

  always @(posedge clk or negedge rst_n)
    if (!rst_n) rc <= 8'b0; else rc <= mon_q;
  assign q_out = rc;
endmodule

// ---- Warning FF on the monitored register ----
module pipe_warning (
  input        clk,
  input        rst_n,
  input  [7:0] a,
  input  [7:0] b,
  output [7:0] q_out,
  output       warning
);
  reg  [7:0] ra, rb, rc;
  wire [7:0] sum, mon_q;

  always @(posedge clk or negedge rst_n)
    if (!rst_n) {ra, rb} <= 16'b0; else {ra, rb} <= {a, b};

  assign sum = ra + rb;

  warning_cell #(.W(8)) u_mon (.clk(clk), .rst_n(rst_n),
                               .d(sum), .q(mon_q), .warning(warning));

  always @(posedge clk or negedge rst_n)
    if (!rst_n) rc <= 8'b0; else rc <= mon_q;
  assign q_out = rc;
endmodule

warning_ff_impl/tb/tb_pipeline.v
//`timescale 1ns/1ps
//============================================================
// tb_pipeline.v -- functional verification of pipe_warning.
// A reference model mirrors the pipeline exactly, so any
// datapath bug is flagged automatically. The warning signal
// is logged (its TIMING correctness is verified later with a
// gate-level SDF sim -- pure RTL has no real delays).
//============================================================
module tb_pipeline;

  reg        clk = 1'b0;
  reg        rst_n = 1'b0;
  reg  [7:0] a = 8'b0;
  reg  [7:0] b = 8'b0;
  wire [7:0] q_out;
  wire       warning;

  // DUT
  pipe_warning dut (.clk(clk), .rst_n(rst_n),
                    .a(a), .b(b), .q_out(q_out), .warning(warning));

  // 1 ns clock
  always #0.5 clk = ~clk;

  // ---- reference model: exact structural mirror of pipe_warning ----
  reg [7:0] m_ra, m_rb, m_mon, m_rc;
  always @(posedge clk or negedge rst_n)
    if (!rst_n) begin
      m_ra <= 8'b0; m_rb <= 8'b0; m_mon <= 8'b0; m_rc <= 8'b0;
    end else begin
      m_ra  <= a;
      m_rb  <= b;
      m_mon <= m_ra + m_rb;
      m_rc  <= m_mon;
    end

  integer i, errors = 0;

  // self-check
  always @(posedge clk)
    if (rst_n) begin
      if (q_out !== m_rc) begin
        $display("MISMATCH t=%0t  expected=%h  got=%h", $time, m_rc, q_out);
        errors = errors + 1;
      end
    end

  initial begin
    $dumpfile("pipe.vcd");
    $dumpvars(0, tb_pipeline);

    rst_n = 1'b0; a = 8'b0; b = 8'b0;
    repeat (2) @(posedge clk);
    rst_n = 1'b1;

    // drive 50 random vectors
    for (i = 0; i < 50; i = i + 1) begin
      @(negedge clk);
      a = $random;
      b = $random;
    end

    repeat (5) @(posedge clk);
    if (errors == 0) $display("PASS: pipeline datapath verified, 0 mismatches.");
    else             $display("FAIL: %0d mismatches.", errors);
    $finish;
  end

endmodule

warning_ff_impl/pipe.vcd
$date
	Sat Jun 27 20:17:02 2026
$end

$version
	Synopsys VCS version T-2022.06-SP2_Full64
$end

$timescale
	1s
$end

$comment Csum: 1 47c34a86fcb34509 $end


$scope module tb_pipeline $end
$var reg 1 ! clk $end
$var reg 1 " rst_n $end
$var reg 8 # a [7:0] $end
$var reg 8 $ b [7:0] $end
$var wire 8 % q_out [7:0] $end
$var wire 1 & warning $end
$var reg 8 ' m_ra [7:0] $end
$var reg 8 ( m_rb [7:0] $end
$var reg 8 ) m_mon [7:0] $end
$var reg 8 * m_rc [7:0] $end
$var integer 32 + i $end
$var integer 32 , errors $end

$scope module dut $end
$var wire 1 - clk $end
$var wire 1 . rst_n $end
$var wire 8 / a [7:0] $end
$var wire 8 0 b [7:0] $end
$var wire 8 % q_out [7:0] $end
$var wire 1 & warning $end
$var reg 8 1 ra [7:0] $end
$var reg 8 2 rb [7:0] $end
$var reg 8 3 rc [7:0] $end
$var wire 8 4 sum [7:0] $end
$var wire 8 5 mon_q [7:0] $end

$scope module u_mon $end
$var wire 1 - clk $end
$var wire 1 . rst_n $end
$var wire 8 4 d [7:0] $end
$var reg 8 6 q [7:0] $end
$var wire 1 & warning $end
$var wire 1 7 mon $end
$var wire 1 8 d_del $end
$var wire 1 9 t_p $end
$var wire 1 : clk_del $end
$var wire 1 ; wd $end
$var wire 1 < set_pulse $end
$var wire 1 = clr $end

$scope module u_dl $end
$var wire 1 7 in $end
$var wire 1 8 out $end
$var wire 5 > n [4:0] $end
$upscope $end


$scope module u_wd $end
$var wire 1 - in $end
$var wire 1 : out $end
$var wire 4 ? n [3:0] $end
$upscope $end


$scope module u_sr $end
$var wire 1 < s $end
$var wire 1 = r $end
$var wire 1 & q $end
$var wire 1 @ qb $end
$upscope $end

$upscope $end

$upscope $end

$upscope $end

$enddefinitions $end

#0
$dumpvars
0!
08
0.
07
0"
b00000000 #
b00000000 $
b00000000 /
b00000000 0
b00000000000000000000000000000000 ,
bxxxxxxxxxxxxxxxxxxxxxxxxxxxxxxxx +
b00000000 )
b00000000 '
b00000000 (
b00000000 *
b00000000 5
b00000 >
b00000000 6
b00000000 %
b00000000 1
b00000000 2
b00000000 3
b00000000 4
b0000 ?
0&
0:
09
0-
0;
0<
1=
1@
$end
#1
1!
1-
0=
1;
b0001 ?
b0011 ?
b0111 ?
b1111 ?
1:
0;
#2
0!
0-
1=
b1110 ?
b1100 ?
b1000 ?
b0000 ?
0:
#3
1!
1-
0=
1;
1"
1.
b00000000000000000000000000000000 +
b0001 ?
b0011 ?
b0111 ?
b1111 ?
1:
0;
#4
0!
0-
1=
b00100100 #
b00100100 /
b10000001 $
b10000001 0
b00000000000000000000000000000001 +
b1110 ?
b1100 ?
b1000 ?
b0000 ?
0:
#5
1!
1-
0=
1;
b0001 ?
b0011 ?
b0111 ?
b1111 ?
1:
0;
b00100100 '
b10000001 (
b00100100 1
b10100101 4
17
b10000001 2
b00001 >
19
b00011 >
b00111 >
b01111 >
b11111 >
18
09
#6
0!
0-
1=
b00001001 #
b00001001 /
b01100011 $
b01100011 0
b00000000000000000000000000000010 +
b1110 ?
b1100 ?
b1000 ?
b0000 ?
0:
#7
1!
1-
0=
1;
b0001 ?
b0011 ?
b0111 ?
b1111 ?
1:
0;
b00001001 '
b01100011 (
b10100101 )
b00001001 1
b01101100 4
07
b01100011 2
b10100101 6
b10100101 5
b11110 >
19
b11100 >
b11000 >
b10000 >
b00000 >
08
09
#8
0!
0-
1=
b00001101 #
b00001101 /
b10001101 $
b10001101 0
b00000000000000000000000000000011 +
b1110 ?
b1100 ?
b1000 ?
b0000 ?
0:
#9
1!
1-
0=
1;
b0001 ?
b0011 ?
b0111 ?
b1111 ?
1:
0;
b00001101 '
b10001101 (
b01101100 )
b10100101 *
b00001101 1
b10011010 4
17
b10001101 2
b10100101 3
b10100101 %
b01101100 6
b01101100 5
b00001 >
19
b00011 >
b00111 >
b01111 >
b11111 >
18
09
#10
0!
0-
1=
b01100101 #
b01100101 /
b00010010 $
b00010010 0
b00000000000000000000000000000100 +
b1110 ?
b1100 ?
b1000 ?
b0000 ?
0:
#11
1!
1-
0=
1;
b0001 ?
b0011 ?
b0111 ?
b1111 ?
1:
0;
b01100101 '
b00010010 (
b10011010 )
b01101100 *
b01100101 1
b01110111 4
07
b00010010 2
b01101100 3
b01101100 %
b10011010 6
b10011010 5
b11110 >
19
b11100 >
b11000 >
b10000 >
b00000 >
08
09
#12
0!
0-
1=
b00000001 #
b00000001 /
b00001101 $
b00001101 0
b00000000000000000000000000000101 +
b1110 ?
b1100 ?
b1000 ?
b0000 ?
0:
#13
1!
1-
0=
1;
b0001 ?
b0011 ?
b0111 ?
b1111 ?
1:
0;
b00000001 '
b00001101 (
b01110111 )
b10011010 *
b00000001 1
b00001110 4
b00001101 2
b10011010 3
b10011010 %
b01110111 6
b01110111 5
#14
0!
0-
1=
b01110110 #
b01110110 /
b00111101 $
b00111101 0
b00000000000000000000000000000110 +
b1110 ?
b1100 ?
b1000 ?
b0000 ?
0:
#15
1!
1-
0=
1;
b0001 ?
b0011 ?
b0111 ?
b1111 ?
1:
0;
b01110110 '
b00111101 (
b00001110 )
b01110111 *
b01110110 1
b10110011 4
17
b00111101 2
b01110111 3
b01110111 %
b00001110 6
b00001110 5
b00001 >
19
b00011 >
b00111 >
b01111 >
b11111 >
18
09
#16
0!
0-
1=
b11101101 #
b11101101 /
b10001100 $
b10001100 0
b00000000000000000000000000000111 +
b1110 ?
b1100 ?
b1000 ?
b0000 ?
0:
#17
1!
1-
0=
1;
b0001 ?
b0011 ?
b0111 ?
b1111 ?
1:
0;
b11101101 '
b10001100 (
b10110011 )
b00001110 *
b11101101 1
b01111001 4
07
b10001100 2
b00001110 3
b00001110 %
b10110011 6
b10110011 5
b11110 >
19
b11100 >
b11000 >
b10000 >
b00000 >
08
09
#18
0!
0-
1=
b11111001 #
b11111001 /
b11000110 $
b11000110 0
b00000000000000000000000000001000 +
b1110 ?
b1100 ?
b1000 ?
b0000 ?
0:
#19
1!
1-
0=
1;
b0001 ?
b0011 ?
b0111 ?
b1111 ?
1:
0;
b11111001 '
b11000110 (
b01111001 )
b10110011 *
b11111001 1
b10111111 4
17
b11000110 2
b10110011 3
b10110011 %
b01111001 6
b01111001 5
b00001 >
19
b00011 >
b00111 >
b01111 >
b11111 >
18
09
#20
0!
0-
1=
b11000101 #
b11000101 /
b10101010 $
b10101010 0
b00000000000000000000000000001001 +
b1110 ?
b1100 ?
b1000 ?
b0000 ?
0:
#21
1!
1-
0=
1;
b0001 ?
b0011 ?
b0111 ?
b1111 ?
1:
0;
b11000101 '
b10101010 (
b10111111 )
b01111001 *
b11000101 1
b01101111 4
07
b10101010 2
b01111001 3
b01111001 %
b10111111 6
b10111111 5
b11110 >
19
b11100 >
b11000 >
b10000 >
b00000 >
08
09
#22
0!
0-
1=
b11100101 #
b11100101 /
b01110111 $
b01110111 0
b00000000000000000000000000001010 +
b1110 ?
b1100 ?
b1000 ?
b0000 ?
0:
#23
1!
1-
0=
1;
b0001 ?
b0011 ?
b0111 ?
b1111 ?
1:
0;
b11100101 '
b01110111 (
b01101111 )
b10111111 *
b11100101 1
b01011100 4
b01110111 2
b10111111 3
b10111111 %
b01101111 6
b01101111 5
#24
0!
0-
1=
b00010010 #
b00010010 /
b10001111 $
b10001111 0
b00000000000000000000000000001011 +
b1110 ?
b1100 ?
b1000 ?
b0000 ?
0:
#25
1!
1-
0=
1;
b0001 ?
b0011 ?
b0111 ?
b1111 ?
1:
0;
b00010010 '
b10001111 (
b01011100 )
b01101111 *
b00010010 1
b10100001 4
17
b10001111 2
b01101111 3
b01101111 %
b01011100 6
b01011100 5
b00001 >
19
b00011 >
b00111 >
b01111 >
b11111 >
18
09
#26
0!
0-
1=
b11110010 #
b11110010 /
b11001110 $
b11001110 0
b00000000000000000000000000001100 +
b1110 ?
b1100 ?
b1000 ?
b0000 ?
0:
#27
1!
1-
0=
1;
b0001 ?
b0011 ?
b0111 ?
b1111 ?
1:
0;
b11110010 '
b11001110 (
b10100001 )
b01011100 *
b11110010 1
b11000000 4
b11001110 2
b01011100 3
b01011100 %
b10100001 6
b10100001 5
#28
0!
0-
1=
b11101000 #
b11101000 /
b11000101 $
b11000101 0
b00000000000000000000000000001101 +
b1110 ?
b1100 ?
b1000 ?
b0000 ?
0:
#29
1!
1-
0=
1;
b0001 ?
b0011 ?
b0111 ?
b1111 ?
1:
0;
b11101000 '
b11000101 (
b11000000 )
b10100001 *
b11101000 1
b10101101 4
b11000101 2
b10100001 3
b10100001 %
b11000000 6
b11000000 5
#30
0!
0-
1=
b01011100 #
b01011100 /
b10111101 $
b10111101 0
b00000000000000000000000000001110 +
b1110 ?
b1100 ?
b1000 ?
b0000 ?
0:
#31
1!
1-
0=
1;
b0001 ?
b0011 ?
b0111 ?
b1111 ?
1:
0;
b01011100 '
b10111101 (
b10101101 )
b11000000 *
b01011100 1
b00011001 4
07
b10111101 2
b11000000 3
b11000000 %
b10101101 6
b10101101 5
b11110 >
19
b11100 >
b11000 >
b10000 >
b00000 >
08
09
#32
0!
0-
1=
b00101101 #
b00101101 /
b01100101 $
b01100101 0
b00000000000000000000000000001111 +
b1110 ?
b1100 ?
b1000 ?
b0000 ?
0:
#33
1!
1-
0=
1;
b0001 ?
b0011 ?
b0111 ?
b1111 ?
1:
0;
b00101101 '
b01100101 (
b00011001 )
b10101101 *
b00101101 1
b10010010 4
17
b01100101 2
b10101101 3
b10101101 %
b00011001 6
b00011001 5
b00001 >
19
b00011 >
b00111 >
b01111 >
b11111 >
18
09
#34
0!
0-
1=
b01100011 #
b01100011 /
b00001010 $
b00001010 0
b00000000000000000000000000010000 +
b1110 ?
b1100 ?
b1000 ?
b0000 ?
0:
#35
1!
1-
0=
1;
b0001 ?
b0011 ?
b0111 ?
b1111 ?
1:
0;
b01100011 '
b00001010 (
b10010010 )
b00011001 *
b01100011 1
b01101101 4
07
b00001010 2
b00011001 3
b00011001 %
b10010010 6
b10010010 5
b11110 >
19
b11100 >
b11000 >
b10000 >
b00000 >
08
09
#36
0!
0-
1=
b10000000 #
b10000000 /
b00100000 $
b00100000 0
b00000000000000000000000000010001 +
b1110 ?
b1100 ?
b1000 ?
b0000 ?
0:
#37
1!
1-
0=
1;
b0001 ?
b0011 ?
b0111 ?
b1111 ?
1:
0;
b10000000 '
b00100000 (
b01101101 )
b10010010 *
b10000000 1
b10100000 4
17
b00100000 2
b10010010 3
b10010010 %
b01101101 6
b01101101 5
b00001 >
19
b00011 >
b00111 >
b01111 >
b11111 >
18
09
#38
0!
0-
1=
b10101010 #
b10101010 /
b10011101 $
b10011101 0
b00000000000000000000000000010010 +
b1110 ?
b1100 ?
b1000 ?
b0000 ?
0:
#39
1!
1-
0=
1;
b0001 ?
b0011 ?
b0111 ?
b1111 ?
1:
0;
b10101010 '
b10011101 (
b10100000 )
b01101101 *
b10101010 1
b01000111 4
07
b10011101 2
b01101101 3
b01101101 %
b10100000 6
b10100000 5
b11110 >
19
b11100 >
b11000 >
b10000 >
b00000 >
08
09
#40
0!
0-
1=
b10010110 #
b10010110 /
b00010011 $
b00010011 0
b00000000000000000000000000010011 +
b1110 ?
b1100 ?
b1000 ?
b0000 ?
0:
#41
1!
1-
0=
1;
b0001 ?
b0011 ?
b0111 ?
b1111 ?
1:
0;
b10010110 '
b00010011 (
b01000111 )
b10100000 *
b10010110 1
b10101001 4
17
b00010011 2
b10100000 3
b10100000 %
b01000111 6
b01000111 5
b00001 >
19
b00011 >
b00111 >
b01111 >
b11111 >
18
09
#42
0!
0-
1=
b00001101 #
b00001101 /
b01010011 $
b01010011 0
b00000000000000000000000000010100 +
b1110 ?
b1100 ?
b1000 ?
b0000 ?
0:
#43
1!
1-
0=
1;
b0001 ?
b0011 ?
b0111 ?
b1111 ?
1:
0;
b00001101 '
b01010011 (
b10101001 )
b01000111 *
b00001101 1
b01100000 4
07
b01010011 2
b01000111 3
b01000111 %
b10101001 6
b10101001 5
b11110 >
19
b11100 >
b11000 >
b10000 >
b00000 >
08
09
#44
0!
0-
1=
b01101011 #
b01101011 /
b11010101 $
b11010101 0
b00000000000000000000000000010101 +
b1110 ?
b1100 ?
b1000 ?
b0000 ?
0:
#45
1!
1-
0=
1;
b0001 ?
b0011 ?
b0111 ?
b1111 ?
1:
0;
b01101011 '
b11010101 (
b01100000 )
b10101001 *
b01101011 1
b01000000 4
b11010101 2
b10101001 3
b10101001 %
b01100000 6
b01100000 5
#46
0!
0-
1=
b00000010 #
b00000010 /
b10101110 $
b10101110 0
b00000000000000000000000000010110 +
b1110 ?
b1100 ?
b1000 ?
b0000 ?
0:
#47
1!
1-
0=
1;
b0001 ?
b0011 ?
b0111 ?
b1111 ?
1:
0;
b00000010 '
b10101110 (
b01000000 )
b01100000 *
b00000010 1
b10110000 4
17
b10101110 2
b01100000 3
b01100000 %
b01000000 6
b01000000 5
b00001 >
19
b00011 >
b00111 >
b01111 >
b11111 >
18
09
#48
0!
0-
1=
b00011101 #
b00011101 /
b11001111 $
b11001111 0
b00000000000000000000000000010111 +
b1110 ?
b1100 ?
b1000 ?
b0000 ?
0:
#49
1!
1-
0=
1;
b0001 ?
b0011 ?
b0111 ?
b1111 ?
1:
0;
b00011101 '
b11001111 (
b10110000 )
b01000000 *
b00011101 1
b11101100 4
b11001111 2
b01000000 3
b01000000 %
b10110000 6
b10110000 5
#50
0!
0-
1=
b00100011 #
b00100011 /
b00001010 $
b00001010 0
b00000000000000000000000000011000 +
b1110 ?
b1100 ?
b1000 ?
b0000 ?
0:
#51
1!
1-
0=
1;
b0001 ?
b0011 ?
b0111 ?
b1111 ?
1:
0;
b00100011 '
b00001010 (
b11101100 )
b10110000 *
b00100011 1
b00101101 4
07
b00001010 2
b10110000 3
b10110000 %
b11101100 6
b11101100 5
b11110 >
19
b11100 >
b11000 >
b10000 >
b00000 >
08
09
#52
0!
0-
1=
b11001010 #
b11001010 /
b00111100 $
b00111100 0
b00000000000000000000000000011001 +
b1110 ?
b1100 ?
b1000 ?
b0000 ?
0:
#53
1!
1-
0=
1;
b0001 ?
b0011 ?
b0111 ?
b1111 ?
1:
0;
b11001010 '
b00111100 (
b00101101 )
b11101100 *
b11001010 1
b00000110 4
b00111100 2
b11101100 3
b11101100 %
b00101101 6
b00101101 5
#54
0!
0-
1=
b11110010 #
b11110010 /
b10001010 $
b10001010 0
b00000000000000000000000000011010 +
b1110 ?
b1100 ?
b1000 ?
b0000 ?
0:
#55
1!
1-
0=
1;
b0001 ?
b0011 ?
b0111 ?
b1111 ?
1:
0;
b11110010 '
b10001010 (
b00000110 )
b00101101 *
b11110010 1
b01111100 4
b10001010 2
b00101101 3
b00101101 %
b00000110 6
b00000110 5
#56
0!
0-
1=
b01000001 #
b01000001 /
b11011000 $
b11011000 0
b00000000000000000000000000011011 +
b1110 ?
b1100 ?
b1000 ?
b0000 ?
0:
#57
1!
1-
0=
1;
b0001 ?
b0011 ?
b0111 ?
b1111 ?
1:
0;
b01000001 '
b11011000 (
b01111100 )
b00000110 *
b01000001 1
b00011001 4
b11011000 2
b00000110 3
b00000110 %
b01111100 6
b01111100 5
#58
0!
0-
1=
b01111000 #
b01111000 /
b10001001 $
b10001001 0
b00000000000000000000000000011100 +
b1110 ?
b1100 ?
b1000 ?
b0000 ?
0:
#59
1!
1-
0=
1;
b0001 ?
b0011 ?
b0111 ?
b1111 ?
1:
0;
b01111000 '
b10001001 (
b00011001 )
b01111100 *
b01111000 1
b00000001 4
b10001001 2
b01111100 3
b01111100 %
b00011001 6
b00011001 5
#60
0!
0-
1=
b11101011 #
b11101011 /
b10110110 $
b10110110 0
b00000000000000000000000000011101 +
b1110 ?
b1100 ?
b1000 ?
b0000 ?
0:
#61
1!
1-
0=
1;
b0001 ?
b0011 ?
b0111 ?
b1111 ?
1:
0;
b11101011 '
b10110110 (
b00000001 )
b00011001 *
b11101011 1
b10100001 4
17
b10110110 2
b00011001 3
b00011001 %
b00000001 6
b00000001 5
b00001 >
19
b00011 >
b00111 >
b01111 >
b11111 >
18
09
#62
0!
0-
1=
b11000110 #
b11000110 /
b10101110 $
b10101110 0
b00000000000000000000000000011110 +
b1110 ?
b1100 ?
b1000 ?
b0000 ?
0:
#63
1!
1-
0=
1;
b0001 ?
b0011 ?
b0111 ?
b1111 ?
1:
0;
b11000110 '
b10101110 (
b10100001 )
b00000001 *
b11000110 1
b01110100 4
07
b10101110 2
b00000001 3
b00000001 %
b10100001 6
b10100001 5
b11110 >
19
b11100 >
b11000 >
b10000 >
b00000 >
08
09
#64
0!
0-
1=
b10111100 #
b10111100 /
b00101010 $
b00101010 0
b00000000000000000000000000011111 +
b1110 ?
b1100 ?
b1000 ?
b0000 ?
0:
#65
1!
1-
0=
1;
b0001 ?
b0011 ?
b0111 ?
b1111 ?
1:
0;
b10111100 '
b00101010 (
b01110100 )
b10100001 *
b10111100 1
b11100110 4
17
b00101010 2
b10100001 3
b10100001 %
b01110100 6
b01110100 5
b00001 >
19
b00011 >
b00111 >
b01111 >
b11111 >
18
09
#66
0!
0-
1=
b00001011 #
b00001011 /
b01110001 $
b01110001 0
b00000000000000000000000000100000 +
b1110 ?
b1100 ?
b1000 ?
b0000 ?
0:
#67
1!
1-
0=
1;
b0001 ?
b0011 ?
b0111 ?
b1111 ?
1:
0;
b00001011 '
b01110001 (
b11100110 )
b01110100 *
b00001011 1
b01111100 4
07
b01110001 2
b01110100 3
b01110100 %
b11100110 6
b11100110 5
b11110 >
19
b11100 >
b11000 >
b10000 >
b00000 >
08
09
#68
0!
0-
1=
b10000101 #
b10000101 /
b01001111 $
b01001111 0
b00000000000000000000000000100001 +
b1110 ?
b1100 ?
b1000 ?
b0000 ?
0:
#69
1!
1-
0=
1;
b0001 ?
b0011 ?
b0111 ?
b1111 ?
1:
0;
b10000101 '
b01001111 (
b01111100 )
b11100110 *
b10000101 1
b11010100 4
17
b01001111 2
b11100110 3
b11100110 %
b01111100 6
b01111100 5
b00001 >
19
b00011 >
b00111 >
b01111 >
b11111 >
18
09
#70
0!
0-
1=
b00111011 #
b00111011 /
b00111010 $
b00111010 0
b00000000000000000000000000100010 +
b1110 ?
b1100 ?
b1000 ?
b0000 ?
0:
#71
1!
1-
0=
1;
b0001 ?
b0011 ?
b0111 ?
b1111 ?
1:
0;
b00111011 '
b00111010 (
b11010100 )
b01111100 *
b00111011 1
b01110101 4
07
b00111010 2
b01111100 3
b01111100 %
b11010100 6
b11010100 5
b11110 >
19
b11100 >
b11000 >
b10000 >
b00000 >
08
09
#72
0!
0-
1=
b01111110 #
b01111110 /
b00010101 $
b00010101 0
b00000000000000000000000000100011 +
b1110 ?
b1100 ?
b1000 ?
b0000 ?
0:
#73
1!
1-
0=
1;
b0001 ?
b0011 ?
b0111 ?
b1111 ?
1:
0;
b01111110 '
b00010101 (
b01110101 )
b11010100 *
b01111110 1
b10010011 4
17
b00010101 2
b11010100 3
b11010100 %
b01110101 6
b01110101 5
b00001 >
19
b00011 >
b00111 >
b01111 >
b11111 >
18
09
#74
0!
0-
1=
b11110001 #
b11110001 /
b11011001 $
b11011001 0
b00000000000000000000000000100100 +
b1110 ?
b1100 ?
b1000 ?
b0000 ?
0:
#75
1!
1-
0=
1;
b0001 ?
b0011 ?
b0111 ?
b1111 ?
1:
0;
b11110001 '
b11011001 (
b10010011 )
b01110101 *
b11110001 1
b11001010 4
b11011001 2
b01110101 3
b01110101 %
b10010011 6
b10010011 5
#76
0!
0-
1=
b01100010 #
b01100010 /
b01001100 $
b01001100 0
b00000000000000000000000000100101 +
b1110 ?
b1100 ?
b1000 ?
b0000 ?
0:
#77
1!
1-
0=
1;
b0001 ?
b0011 ?
b0111 ?
b1111 ?
1:
0;
b01100010 '
b01001100 (
b11001010 )
b10010011 *
b01100010 1
b10101110 4
b01001100 2
b10010011 3
b10010011 %
b11001010 6
b11001010 5
#78
0!
0-
1=
b10011111 #
b10011111 /
b10001111 $
b10001111 0
b00000000000000000000000000100110 +
b1110 ?
b1100 ?
b1000 ?
b0000 ?
0:
#79
1!
1-
0=
1;
b0001 ?
b0011 ?
b0111 ?
b1111 ?
1:
0;
b10011111 '
b10001111 (
b10101110 )
b11001010 *
b10011111 1
b00101110 4
07
b10001111 2
b11001010 3
b11001010 %
b10101110 6
b10101110 5
b11110 >
19
b11100 >
b11000 >
b10000 >
b00000 >
08
09
#80
0!
0-
1=
b11111000 #
b11111000 /
b10110111 $
b10110111 0
b00000000000000000000000000100111 +
b1110 ?
b1100 ?
b1000 ?
b0000 ?
0:
#81
1!
1-
0=
1;
b0001 ?
b0011 ?
b0111 ?
b1111 ?
1:
0;
b11111000 '
b10110111 (
b00101110 )
b10101110 *
b11111000 1
b10101111 4
17
b10110111 2
b10101110 3
b10101110 %
b00101110 6
b00101110 5
b00001 >
19
b00011 >
b00111 >
b01111 >
b11111 >
18
09
#82
0!
0-
1=
b10011111 #
b10011111 /
b01011100 $
b01011100 0
b00000000000000000000000000101000 +
b1110 ?
b1100 ?
b1000 ?
b0000 ?
0:
#83
1!
1-
0=
1;
b0001 ?
b0011 ?
b0111 ?
b1111 ?
1:
0;
b10011111 '
b01011100 (
b10101111 )
b00101110 *
b10011111 1
b11111011 4
b01011100 2
b00101110 3
b00101110 %
b10101111 6
b10101111 5
#84
0!
0-
1=
b01011011 #
b01011011 /
b10001001 $
b10001001 0
b00000000000000000000000000101001 +
b1110 ?
b1100 ?
b1000 ?
b0000 ?
0:
#85
1!
1-
0=
1;
b0001 ?
b0011 ?
b0111 ?
b1111 ?
1:
0;
b01011011 '
b10001001 (
b11111011 )
b10101111 *
b01011011 1
b11100100 4
b10001001 2
b10101111 3
b10101111 %
b11111011 6
b11111011 5
#86
0!
0-
1=
b01001001 #
b01001001 /
b11010000 $
b11010000 0
b00000000000000000000000000101010 +
b1110 ?
b1100 ?
b1000 ?
b0000 ?
0:
#87
1!
1-
0=
1;
b0001 ?
b0011 ?
b0111 ?
b1111 ?
1:
0;
b01001001 '
b11010000 (
b11100100 )
b11111011 *
b01001001 1
b00011001 4
07
b11010000 2
b11111011 3
b11111011 %
b11100100 6
b11100100 5
b11110 >
19
b11100 >
b11000 >
b10000 >
b00000 >
08
09
